slurmqueen/__init__.py
slurmqueen/dashboard.py
slurmqueen/experiment.py
slurmqueen/interactive.py
slurmqueen/slurm_experiment.py
slurmqueen/slurm_script.py
slurmqueen/ssh_client.py
slurmqueen-1.2.2.dist-info/DESCRIPTION.rst
slurmqueen-1.2.2.dist-info/METADATA
slurmqueen-1.2.2.dist-info/RECORD
slurmqueen-1.2.2.dist-info/WHEEL
slurmqueen-1.2.2.dist-info/metadata.json
slurmqueen-1.2.2.dist-info/top_level.txt
