Metadata-Version: 2.0
Name: slurmqueen
Version: 1.2.2
Summary: A Python 3 library for automatically running experiments using a Slurm cluster
Home-page: https://github.com/Kasekopf/SlurmQueen
Author: Jeffrey Dudek
Author-email: jeffreydudek@gmail.com
License: MIT
Platform: Posix; MacOS X; Windows
Classifier: Programming Language :: Python :: 3
Classifier: License :: OSI Approved :: MIT License
Classifier: Operating System :: OS Independent
Requires-Dist: paramiko
Requires-Dist: pandas
